README.md
setup.py
navdreams/__init__.py
navdreams/archiveenv.py
navdreams/auto_debug.py
navdreams/crowd_sim_info.py
navdreams/custom_policy.py
navdreams/dreamenv3d.py
navdreams/encodedenv3d.py
navdreams/helpers.py
navdreams/mlagents_gym_wrapper.py
navdreams/navrep3danyenv.py
navdreams/navrep3dtrainencodedenv.py
navdreams/navrep3dtrainenv.py
navdreams/recurrent_wrapper.py
navdreams/rssm.py
navdreams/rssm_a0.py
navdreams/sb3_callbacks.py
navdreams/socket_handler.py
navdreams/transformerL.py
navdreams/tssm.py
navdreams/worldmodel.py
navdreams/zero.py
navdreams.egg-info/PKG-INFO
navdreams.egg-info/SOURCES.txt
navdreams.egg-info/dependency_links.txt
navdreams.egg-info/requires.txt
navdreams.egg-info/top_level.txt