Metadata-Version: 2.1
Name: navdreams
Version: 0.0.11
Summary: NavDreams python package, including simulator and tools
Home-page: UNKNOWN
Author: Daniel Dugas
License: UNKNOWN
Platform: UNKNOWN
Requires-Python: >=3.6
